helloworld3663.py
helloworld3663-0.0.1.dist-info/LICENSE.txt
helloworld3663-0.0.1.dist-info/METADATA
helloworld3663-0.0.1.dist-info/WHEEL
helloworld3663-0.0.1.dist-info/top_level.txt
helloworld3663-0.0.1.dist-info/RECORD
